{"is_source_file": true, "format": "TypeScript/TSX", "description": "This file defines a SearchBar React component using Qwik framework, including its properties, internal signals, and event handling logic.", "external_files": ["@builder.io/qwik"], "external_methods": ["component$", "$", "useSignal", "PropFunction"], "published": ["SearchBarProps", "SearchBar"], "classes": [], "methods": [{"name": "SearchBar", "description": "A functional component that renders a search input box and triggers onSearch$ callback on input change."}], "calls": ["useSignal", "component$", "$"], "search-terms": ["SearchBar", "search input", "Qwik component", "search event handling", "TypeScript React component"], "state": 2, "file_id": 23, "knowledge_revision": 48, "git_revision": "", "ctags": [], "hash": "d219cfadcdedd17066d5266f81865892", "format-version": 4, "code-base-name": "notes_frontend", "filename": "notes_frontend/src/components/search-bar.tsx", "revision_history": [{"48": ""}]}